{
  "sources": [
    {
      "id": "source_001",
      "name": "苏轼出生与眉山家学",
      "type": "史料",
      "link": "《宋史·苏轼列传》（卷三百三十八），中华书局点校本",
      "usage": "S10-S12 序幕：眉山少年",
      "summary": "苏轼生于宋仁宗景祐三年（1037年）于眉山，字子瞻，号东坡居士。父苏洵，弟苏辙，三人并称'三苏'。",
      "isHistoricalFact": true,
      "isAdaptation": false
    },
    {
      "id": "source_002",
      "name": "苏辙与苏轼兄弟关系",
      "type": "史料",
      "link": "《宋史·苏辙列传》（卷三百三十九），中华书局点校本",
      "usage": "S12 兄弟并行, S24 子由救援卡",
      "summary": "苏辙，字子由，苏轼之弟。乌台诗案时上书愿以官职赎兄罪。",
      "isHistoricalFact": true,
      "isAdaptation": false
    },
    {
      "id": "source_003",
      "name": "乌台诗案",
      "type": "史料",
      "link": "《宋史·苏轼列传》（卷三百三十八），中华书局点校本；又见孔凡礼点校《苏轼年谱》，中华书局2005年版",
      "usage": "S22-S25 乌台风暴",
      "summary": "元丰二年（1079年），苏轼因诗文被弹劾入狱，后贬黄州。御史台弹劾其作诗讽刺新法。",
      "isHistoricalFact": true,
      "isAdaptation": false
    },
    {
      "id": "source_004",
      "name": "苏辙救兄：《为兄轼下狱上书》",
      "type": "史料·作品原文",
      "link": "《苏辙文集》卷二十《论时事状》，曾枣庄、马德富校点，上海古籍出版社1987年版；亦见《全宋文》册四十六，巴蜀书社",
      "usage": "S23-S24 子由救援",
      "summary": "苏辙在兄长苏轼下狱后上书，请求以自身官职为兄赎罪。游戏中的\"子由救援卡\"基于这一史实关系进行机制化改编。具体原文引用需以正式底本（《苏辙集》《栾城集》或《全宋文》）复核。",
      "isHistoricalFact": true,
      "isAdaptation": true,
      "note": "部分网络版本流传的文字片段未经严谨考证，游戏不采用此类未经核实的引用，仅保留史实关系描述。"
    },
    {
      "id": "source_005",
      "name": "黄州贬谪",
      "type": "史料",
      "link": "《宋史·苏轼列传》（卷三百三十八），中华书局点校本；孔凡礼点校《苏轼年谱》卷二十二，中华书局2005年版",
      "usage": "S25-S34 黄州阶段",
      "summary": "乌台诗案后，元丰三年（1080年）苏轼贬为黄州团练副使，本州安置，不得签书公事。",
      "isHistoricalFact": true,
      "isAdaptation": false
    },
    {
      "id": "source_006",
      "name": "《猪肉颂》",
      "type": "作品原文",
      "link": "《东坡集》卷七十一；又见《苏轼文集》卷六十六，中华书局点校本1986年版",
      "usage": "S33-S34 东坡肉",
      "summary": "《猪肉颂》写黄州猪肉价格：'黄州好猪肉，价贱如泥土。贵者不肯吃，贫者不解煮。'洗净，慢着火……",
      "isHistoricalFact": true,
      "isAdaptation": false
    },
    {
      "id": "source_007",
      "name": "《记承天寺夜游》",
      "type": "作品原文",
      "link": "《东坡集》卷六十九；又见《苏轼文集》卷六十八，中华书局点校本1986年版",
      "usage": "S40-S43 承天寺夜游",
      "summary": "原文：\"元丰六年十月十二日夜，解衣欲睡，月色入户，欣然起行。念无与为乐者，遂至承天寺寻张怀民。怀民亦未寝，相与步于中庭。庭下如积水空明，水中藻荇交横，盖竹柏影也。何夜无月？何处无竹柏？但少闲人如吾两人者耳。\"（据中华书局点校本《苏轼文集》卷六十八，1986年版）",
      "isHistoricalFact": true,
      "isAdaptation": false,
      "note": "部分通行版本\"念无与为乐者\"作\"念无与乐者\"，系传本异文，此处从中华书局点校本《苏轼文集》。游戏内所有相关文本统一使用此底本。"
    },
    {
      "id": "source_008",
      "name": "张怀民",
      "type": "史料·人物",
      "link": "《东坡志林》卷二'承天夜游'条；又见《宋史》无专传，事迹散见苏轼诗文；可参朱刚《苏轼评传》，南京大学出版社2004年版",
      "usage": "S41-S42 怀民夜游",
      "summary": "张怀民，苏轼黄州时期友人。苏轼《记承天寺夜游》记其事：\"遂至承天寺寻张怀民。怀民亦未寝，相与步于中庭。\"其名字、字号各文献记载不一，游戏仅使用该文所记确定信息，不采用有争议的身份描述。",
      "isHistoricalFact": false,
      "isAdaptation": true,
      "note": "网络流传的相关考证文字未经理据核实，游戏正式版仅使用《记承天寺夜游》原文可确定信息，不采用任何未经核实的字号、别名。"
    },
    {
      "id": "source_009",
      "name": "廉洁文化与公私边界",
      "type": "现代研究资料",
      "link": "参考：徐大同主编《中国传统政治文化》，天津人民出版社2001年版；王杰、祝曙光《中国廉政史》，中国方正出版社2014年版；中央纪委国家监委网站'中国传统廉政思想'专题",
      "usage": "游戏设计理念",
      "summary": "传统廉洁观强调公私分明，但不是冷酷无情，而是在人情往来中保持清醒的边界意识。本游戏账目系统参考这一理念设计。",
      "isHistoricalFact": false,
      "isAdaptation": true
    },
    {
      "id": "source_010",
      "name": "游戏改编说明",
      "type": "项目资料",
      "link": "本游戏原创",
      "usage": "所有场景",
      "summary": "本游戏为互动叙事游戏，采用'子由救援卡''村民送肉''怀民状态检测''预算小游戏'等游戏化机制，用于增强玩家参与感，并非真实历史记录。游戏强调识别人情是否附带公共交换，在困境中保持人格完整。",
      "isHistoricalFact": false,
      "isAdaptation": true
    }
  ]
}